fastapi_rabbit_admin-0.1.25.dist-info/licenses/LICENSE
rabbit_admin/__init__.py
rabbit_admin/admin.py
rabbit_admin/adminV2.py
rabbit_admin/decor.py
rabbit_admin/static/favicon.ico
rabbit_admin/static/index.html
rabbit_admin/static/assets/AdminPage-BskEeZYD.js
rabbit_admin/static/assets/CreatePage-B0281ZCQ.js
rabbit_admin/static/assets/DetailPage-DG9hOFFA.js
rabbit_admin/static/assets/ErrorNotFound-CfiZheOn.js
rabbit_admin/static/assets/Eva-Icons-CJip5A4A.woff2
rabbit_admin/static/assets/Eva-Icons-_dyB-OSJ.woff
rabbit_admin/static/assets/KFOMCnqEu92Fr1ME7kSn66aGLdTylUAMQXC89YmC2DPNWuYjalmUiAw-BepdiOnY.woff
rabbit_admin/static/assets/KFOMCnqEu92Fr1ME7kSn66aGLdTylUAMQXC89YmC2DPNWuZtalmUiAw-4ZhHFPot.woff
rabbit_admin/static/assets/KFOMCnqEu92Fr1ME7kSn66aGLdTylUAMQXC89YmC2DPNWuaabVmUiAw-CNa4tw4G.woff
rabbit_admin/static/assets/KFOMCnqEu92Fr1ME7kSn66aGLdTylUAMQXC89YmC2DPNWub2bVmUiAw-CHKg1YId.woff
rabbit_admin/static/assets/KFOMCnqEu92Fr1ME7kSn66aGLdTylUAMQXC89YmC2DPNWubEbFmUiAw-yBxCyPWP.woff
rabbit_admin/static/assets/KFOMCnqEu92Fr1ME7kSn66aGLdTylUAMQXC89YmC2DPNWubEbVmUiAw-3fZ6d7DD.woff
rabbit_admin/static/assets/ListPage-Bu3OEVWr.js
rabbit_admin/static/assets/MainLayout-B349vTHO.js
rabbit_admin/static/assets/QSelect-C8ptnavx.js
rabbit_admin/static/assets/QTable-D20vF28M.js
rabbit_admin/static/assets/SelectField-3PCVse26.js
rabbit_admin/static/assets/TouchPan-BxbE_y17.js
rabbit_admin/static/assets/axios-BPWCx0t4.js
rabbit_admin/static/assets/crud-BfVkPVC6.js
rabbit_admin/static/assets/flUhRq6tzZclQEJ-Vdg-IuiaDsNa-Dr0goTwe.woff
rabbit_admin/static/assets/flUhRq6tzZclQEJ-Vdg-IuiaDsNcIhQ8tQ-D-x-0Q06.woff2
rabbit_admin/static/assets/format-C6RmEeGd.js
rabbit_admin/static/assets/index-BZJcJJsl.css
rabbit_admin/static/assets/index-O_ON0DDw.js
rabbit_admin/static/icons/favicon-128x128.png
rabbit_admin/static/icons/favicon-16x16.png
rabbit_admin/static/icons/favicon-32x32.png
rabbit_admin/static/icons/favicon-96x96.png
fastapi_rabbit_admin-0.1.25.dist-info/METADATA
fastapi_rabbit_admin-0.1.25.dist-info/WHEEL
fastapi_rabbit_admin-0.1.25.dist-info/top_level.txt
fastapi_rabbit_admin-0.1.25.dist-info/RECORD
