Metadata-Version: 2.4
Name: fastapi-rabbit-admin
Version: 0.1.25
Summary: A FastAPI admin dashboard for Tortoise ORM models
Home-page: https://github.com/yourusername/rabbit-admin
Author: Your Name
Author-email: Your Name <your.email@example.com>
License: MIT
Project-URL: Homepage, https://github.com/yourusername/rabbit-admin
Project-URL: Documentation, https://github.com/yourusername/rabbit-admin
Project-URL: Repository, https://github.com/yourusername/rabbit-admin
Classifier: Development Status :: 3 - Alpha
Classifier: Intended Audience :: Developers
Classifier: Topic :: Software Development :: Libraries :: Application Frameworks
Classifier: Programming Language :: Python :: 3
Classifier: Programming Language :: Python :: 3.8
Classifier: Programming Language :: Python :: 3.9
Classifier: Programming Language :: Python :: 3.10
Classifier: Programming Language :: Python :: 3.11
Requires-Python: >=3.8
License-File: LICENSE
Requires-Dist: fastapi>=0.104.0
Requires-Dist: tortoise-orm>=0.20.0
Requires-Dist: pydantic>=2.0.0
Provides-Extra: dev
Requires-Dist: pytest>=7.0.0; extra == "dev"
Requires-Dist: pytest-asyncio>=0.21.0; extra == "dev"
Requires-Dist: aerich>=0.7.0; extra == "dev"
Dynamic: author
Dynamic: home-page
Dynamic: license-file
Dynamic: requires-python
